PrimeNumberDetector/PrimeNumberDetector.sv
`timescale 1ns / 100ps // Each time step will be 1 ns, and the resolution of the simulation will be in steps of 100 ps

module pnd(
    input wire a,
    input wire b,
    input wire c,
    output p
    );

    assign p = (~c && b) || (a && c);

endmodule

module pnd_tb;
    reg A;
    reg B;
    reg C;
    reg P;
    integer input_comb;

    pnd my_pnd(
        .a(A),
        .b(B),
        .c(C),
        .p(P)
    );

    // Monitor the outputs
    initial begin
        // $monitor("Time: %0t | C: %d | B: %d | A: %d | P: %d", $time, C, B, A, P);
        $monitor("Time: %0t | input: %0d | P: %d", $time, input_comb, P);
        $dumpfile("pnd_tb.vcd");
        $dumpvars(0, pnd_tb);
    end

    initial
        begin
               C = 0; B = 0; A = 0;
            #5 C = 0; B = 0; A = 1;
            #5 C = 0; B = 1; A = 0;
            #5 C = 0; B = 1; A = 1;
            #5 C = 1; B = 0; A = 0;
            #5 C = 1; B = 0; A = 1;
            #5 C = 1; B = 1; A = 0;
            #5 C = 1; B = 1; A = 1;
            #5
            $finish;
        end

    // Update this block everytime C, B, or A change
    always @(C, B, A) begin
        input_comb = {C, B, A}; // Concatenate C, B, A to form a binary number
    end

endmodule

PrimeNumberDetector/pnd_tb.vcd
$date
	Sun Nov 24 17:47:11 2024
$end
$version
	Icarus Verilog
$end
$timescale
	100ps
$end
$scope module pnd_tb $end
$var wire 1 ! P $end
$var reg 1 " A $end
$var reg 1 # B $end
$var reg 1 $ C $end
$var integer 32 % input_comb [31:0] $end
$scope module my_pnd $end
$var wire 1 " a $end
$var wire 1 # b $end
$var wire 1 $ c $end
$var wire 1 ! p $end
$upscope $end
$upscope $end
$enddefinitions $end
$comment Show the parameter values. $end
$dumpall
$end
#0
$dumpvars
b0 %
0$
0#
0"
0!
$end
#50
b1 %
1"
#100
1!
b10 %
0"
1#
#150
b11 %
1"
#200
0!
b100 %
0"
0#
1$
#250
1!
b101 %
1"
#300
0!
b110 %
0"
1#
#350
1!
b111 %
1"
