SimpleMux/simpleMux.sv
module mux (input wire a, b, s, output wire o);
    wire ns;
    wire sa;
    wire nsb;

    assign ns  = !s;
    assign sa  = a & s;
    assign nsb = b & ns;
    assign o   = sa | nsb;

endmodule

module mux_tb;
    reg a, b, s, o;

    mux dut(
        .a(a),
        .b(b),
        .s(s),
        .o(o)
    );

    // Monitor the outputs
    initial begin
        $monitor("Time: %0t | a: %d | b: %d | s: %d | o: %d", $time, a, b, s, o);
        $dumpfile("mux_tb.vcd");
        $dumpvars(0, mux_tb);
    end

    // s = 0 selects b, s = 1 selects a
    initial begin
           a = 0; b = 0; s = 0; // o = 0
        #5 a = 0; b = 0; s = 1; // o = 0
        #5 a = 0; b = 1; s = 0; // o = 1
        #5 a = 0; b = 1; s = 1; // o = 0
        #5 a = 1; b = 0; s = 0; // o = 0
        #5 a = 1; b = 0; s = 1; // o = 1
        #5 a = 1; b = 1; s = 0; // o = 1
        #5 a = 1; b = 1; s = 1; // o = 1
    end

endmodule

SimpleMux/mux_tb.vcd
$date
	Mon Nov 18 23:07:49 2024
$end
$version
	Icarus Verilog
$end
$timescale
	1s
$end
$scope module mux_tb $end
$var wire 1 ! o $end
$var reg 1 " a $end
$var reg 1 # b $end
$var reg 1 $ s $end
$scope module dut $end
$var wire 1 " a $end
$var wire 1 # b $end
$var wire 1 % nsb $end
$var wire 1 ! o $end
$var wire 1 $ s $end
$var wire 1 & sa $end
$var wire 1 ' ns $end
$upscope $end
$upscope $end
$enddefinitions $end
$comment Show the parameter values. $end
$dumpall
$end
#0
$dumpvars
1'
0&
0%
0$
0#
0"
0!
$end
#5
0'
1$
#10
1!
1%
1'
0$
1#
#15
0!
0%
0'
1$
#20
1'
0$
0#
1"
#25
1!
1&
0'
1$
#30
0&
1%
1'
0$
1#
#35
1&
0%
0'
1$
